[{"assetId":9837692791,"name":"Picnic Road"},{"assetId":9837677686,"name":"The Nightmare Woods ( Run Run Rottytops )"},{"assetId":9837649145,"name":"Shantae Riskys Revenge OST File Select"},{"assetId":9837634222,"name":"Fire Emblem Echoes Shadows of Valentia Title"},{"assetId":9837548338,"name":"Sans"},{"assetId":9837535206,"name":"Efteling muziek - Vogel Rok - Broedplaats"},{"assetId":9837507285,"name":"Find the Chomiks OST 091 - Strum of Lost Souls"},{"assetId":9837480052,"name":"Efteling muziek - De Zes Zwanen"},{"assetId":9837190874,"name":"Creo - Rivals"},{"assetId":9837186742,"name":"【SDVX】-RoughSketch-－-666-【NOFX】"},{"assetId":9836901497,"name":"Bebplays - Achievements"},{"assetId":9836496580,"name":"kazunocobit - unconnectable"},{"assetId":9836389210,"name":"Kshiraki - Pico"},{"assetId":9836321620,"name":"kazunocobit - 咲いて枯れて (Blooming and withering)"},{"assetId":9835432960,"name":"you were wrong go back"},{"assetId":9835430711,"name":"world's end valentine"},{"assetId":9835425300,"name":"endgame"},{"assetId":9835117513,"name":"Airwolf Main Theme - DJromain Remix"},{"assetId":9834530417,"name":"kamome #### - archive - -zip"},{"assetId":9834520815,"name":"Desemon - Hellcat ##### ###########"},{"assetId":9834491147,"name":"Dimrain47 - surface"},{"assetId":9834474297,"name":"newlard remix - floor baba wigglecore"},{"assetId":9834457787,"name":"Earthbound - OK DESU KA?"},{"assetId":9834225514,"name":"Guardian of The Former Seas"},{"assetId":9834093335,"name":"Unholy Insurgency"},{"assetId":9833477340,"name":"Terraria Calamity Mod - Hadopelagic Pressure"},{"assetId":9833193339,"name":"funny ewoijoif ewjoi ### owifoiew ###"},{"assetId":9832932923,"name":"funny song part 3"},{"assetId":9832256276,"name":"funny song part 2"},{"assetId":9832223201,"name":"Bubbles - Tokyo Machine"},{"assetId":9832093557,"name":"infinite falling tone"},{"assetId":9831802814,"name":"O FORTUNA BATTLE CATS"},{"assetId":9831796467,"name":"BATTLE CATS INTO THE FUTURE THEME #1"},{"assetId":9831198726,"name":"Breakup Simulator Lite"},{"assetId":9829854315,"name":"Light it up"},{"assetId":9829777262,"name":"Completeness under Incompleteness"},{"assetId":9829739826,"name":"Camellia - Light it up"},{"assetId":9829714740,"name":"Siliconvalleysyrup.Temp"},{"assetId":9829561883,"name":"Se-U-Ra - The Endless for Traveler (Long ver)"},{"assetId":9829333662,"name":"Sakuzyo - Scheol "},{"assetId":9829245534,"name":"MoAE: - Fixcyan"},{"assetId":9829149620,"name":"MoAE: - LixeRio"},{"assetId":9829019471,"name":"L aventale"},{"assetId":9828563691,"name":"Sans"},{"assetId":9828504556,"name":"Kirby Super Star - Cocoa Caves"},{"assetId":9827995129,"name":"To Make You Happy "},{"assetId":9827982122,"name":"To Make You Happy "},{"assetId":9827968389,"name":"To Make You Happy "},{"assetId":9827933331,"name":"cringy music from poland 😎🥶"},{"assetId":9827698099,"name":"Let's Dance"},{"assetId":9827372307,"name":"Kuya's Mansion: Silhouette"},{"assetId":9827369921,"name":"Kuya's Mansion: Vanessa Wants to Play"},{"assetId":9827211574,"name":"FOOOOOOOOOL"},{"assetId":9827058433,"name":"necro fantasia"},{"assetId":9826839773,"name":"They All Look The Same (Connor) "},{"assetId":9826765405,"name":"Holy Knight - Eyemedia"},{"assetId":9826718498,"name":"meganeko - ### battle jam"},{"assetId":9826705696,"name":"Rick Astley - Never Gonna Give You Up "},{"assetId":9826681392,"name":"servants of the scourge"},{"assetId":9826663163,"name":"Waterflame Combo-Breaker-Japan"},{"assetId":9826644628,"name":"creo summit"},{"assetId":9826642928,"name":"KoF XV - Now or Never"},{"assetId":9826441912,"name":"Bossfight - ##### ##### Oh It hurts"},{"assetId":9826413575,"name":"Creo - Challenger "},{"assetId":9826287906,"name":"Jewelz & Sparks - Traffic "},{"assetId":9826240014,"name":"Shinrog - Infertehno #"},{"assetId":9826187562,"name":"Sonic Lost World Tropical Coast Act #"},{"assetId":9826111583,"name":"Creo_-_Black_Ice"},{"assetId":9825978707,"name":"Slow "},{"assetId":9825941745,"name":"########### - Ballad Of The Trees"},{"assetId":9825865641,"name":"Making Audio"},{"assetId":9825826515,"name":"DM Dokuro - Hadopelagic Pressure"},{"assetId":9825825361,"name":"Noise Ib ###"},{"assetId":9825820395,"name":"DM Dokuro - Threats of The Ocean Floor"},{"assetId":9825812530,"name":"Eisoptrophobia"},{"assetId":9825745550,"name":"Corelli La Folia IB"},{"assetId":9825658296,"name":"Ib ### - Memory"},{"assetId":9825427999,"name":"A Hat in Time ### mustache girl EX"},{"assetId":9825371150,"name":"The Carebear - A1- I'll Be Remembering You"},{"assetId":9825368824,"name":"Blood #########"},{"assetId":9825248439,"name":"The Step Below Hell"},{"assetId":9825238481,"name":"J1 - Post Awareness Confusions (Ending)"},{"assetId":9825158616,"name":"Universal Collapse"},{"assetId":9824178745,"name":"DM Dokuro - Sanctuary"},{"assetId":9824106012,"name":"[breakbeats]migino - 第一宇宙速度"},{"assetId":9823892024,"name":"Epic Cryogen Remix"},{"assetId":9822719241,"name":"Asleep Atop An Atom"},{"assetId":9822690060,"name":"pilotredsun - riverdance"},{"assetId":9822498321,"name":"Kuya's Mansion: The Prophecy"},{"assetId":9822497112,"name":"Camellia - ##### AREA ##"},{"assetId":9822455437,"name":"Mama's Story"},{"assetId":9820946621,"name":"cobaltic"},{"assetId":9819952522,"name":"Distortion"},{"assetId":9819498567,"name":"Old Duke (Toxic Wisdom) Calamity Terraria"},{"assetId":9819236671,"name":"Tainted Ambition"},{"assetId":9819125359,"name":"Superposition"},{"assetId":9818764537,"name":"Alesso Payday"},{"assetId":9818739378,"name":"Razormind"},{"assetId":9818729899,"name":"Break the Rules"},{"assetId":9818722088,"name":"cloaker noise"}]